django_sonar/__init__.py
django_sonar/admin.py
django_sonar/apps.py
django_sonar/db_router.py
django_sonar/mixins.py
django_sonar/urls.py
django_sonar/utils.py
django_sonar/views.py
django_sonar/core/__init__.py
django_sonar/core/collectors.py
django_sonar/core/filters.py
django_sonar/core/parsers.py
django_sonar/management/commands/clear_sonar_data.py
django_sonar/middlewares/__init__.py
django_sonar/middlewares/requests.py
django_sonar/migrations/0001_initial.py
django_sonar/migrations/0002_add_query_count.py
django_sonar/migrations/0003_alter_sonarrequest_path.py
django_sonar/migrations/__init__.py
django_sonar/models/__init__.py
django_sonar/models/sonar_data.py
django_sonar/models/sonar_request.py
django_sonar/static/django_sonar/css/.DS_Store
django_sonar/static/django_sonar/css/bootstrap-icons.min.css
django_sonar/static/django_sonar/css/bootstrap.min.css
django_sonar/static/django_sonar/css/dark-theme.css
django_sonar/static/django_sonar/css/django-sonar.css
django_sonar/static/django_sonar/css/fonts/bootstrap-icons.woff2
django_sonar/static/django_sonar/js/bootstrap.bundle.min.js
django_sonar/static/django_sonar/js/htmx.min.js
django_sonar/static/django_sonar/js/sql-formatter.min.js
django_sonar/static/django_sonar/media/logos/favicon.png
django_sonar/templates/django_sonar/auth/denied.html
django_sonar/templates/django_sonar/auth/login.html
django_sonar/templates/django_sonar/dumps/index.html
django_sonar/templates/django_sonar/exceptions/index.html
django_sonar/templates/django_sonar/home/index.html
django_sonar/templates/django_sonar/layouts/auth.html
django_sonar/templates/django_sonar/queries/detail.html
django_sonar/templates/django_sonar/queries/index.html
django_sonar/templates/django_sonar/requests/detail.html
django_sonar/templates/django_sonar/requests/detail_dumps.html
django_sonar/templates/django_sonar/requests/detail_exception.html
django_sonar/templates/django_sonar/requests/detail_headers.html
django_sonar-0.3.0.dist-info/licenses/LICENSE
django_sonar-0.3.0.dist-info/METADATA
django_sonar-0.3.0.dist-info/WHEEL
django_sonar-0.3.0.dist-info/top_level.txt
django_sonar-0.3.0.dist-info/RECORD
