Metadata-Version: 2.4
Name: django_sonar
Version: 0.3.0
Summary: The missing debug tool for Django, inspired by Telescope.
Author-email: Metalogico <michele.brandolin@gmail.com>
License: MIT
Project-URL: Homepage, https://github.com/metalogico/django-sonar
Project-URL: Issues, https://github.com/metalogico/django-sonar/issues
Project-URL: Download, https://pypi.org/project/django-sonar/
Classifier: Development Status :: 3 - Alpha
Classifier: Environment :: Web Environment
Classifier: Framework :: Django
Classifier: Framework :: Django :: 4.2
Classifier: Framework :: Django :: 5.0
Classifier: Intended Audience :: Developers
Classifier: License :: OSI Approved :: MIT License
Classifier: Operating System :: OS Independent
Classifier: Programming Language :: Python
Classifier: Programming Language :: Python :: 3 :: Only
Classifier: Programming Language :: Python :: 3.8
Classifier: Programming Language :: Python :: 3.9
Classifier: Programming Language :: Python :: 3.10
Classifier: Programming Language :: Python :: 3.11
Classifier: Programming Language :: Python :: 3.12
Requires-Python: >=3.8
License-File: LICENSE
Requires-Dist: Django>=4.2.9
Requires-Dist: sqlparse>=0.2
Dynamic: license-file
